{
  "annotations": {
    "list": [
      {
        "builtIn": 1,
        "datasource": {
          "type": "grafana",
          "uid": "-- Grafana --"
        },
        "enable": true,
        "hide": true,
        "iconColor": "rgba(0, 211, 255, 1)",
        "name": "Annotations & Alerts",
        "type": "dashboard"
      }
    ]
  },
  "editable": true,
  "graphTooltip": 1,
  "schemaVersion": 39,
  "version": 2,
  "refresh": "30s",
  "tags": [
    "ecotrack",
    "technique",
    "sre"
  ],
  "timezone": "",
  "title": "ECOTRACK - Technique / Plateforme",
  "uid": "ecotrack-technique",
  "time": {
    "from": "now-6h",
    "to": "now"
  },
  "templating": {
    "list": []
  },
  "panels": [
    {
      "type": "stat",
      "title": "Cibles UP",
      "datasource": {
        "type": "prometheus",
        "uid": "ECOTRACK_PROM"
      },
      "gridPos": {
        "h": 4,
        "w": 4,
        "x": 0,
        "y": 0
      },
      "fieldConfig": {
        "defaults": {
          "unit": "short",
          "thresholds": {
            "mode": "absolute",
            "steps": [
              {
                "color": "red",
                "value": null
              },
              {
                "color": "green",
                "value": 1
              }
            ]
          },
          "color": {
            "mode": "thresholds"
          }
        },
        "overrides": []
      },
      "options": {
        "reduceOptions": {
          "calcs": [
            "lastNotNull"
          ],
          "fields": "",
          "values": false
        },
        "colorMode": "value",
        "graphMode": "none",
        "justifyMode": "auto",
        "textMode": "auto",
        "orientation": "auto"
      },
      "targets": [
        {
          "datasource": {
            "type": "prometheus",
            "uid": "ECOTRACK_PROM"
          },
          "editorMode": "code",
          "expr": "sum(up)",
          "legendFormat": "__auto",
          "range": true,
          "instant": false,
          "refId": "A"
        }
      ],
      "id": 1
    },
    {
      "type": "stat",
      "title": "Cibles totales",
      "datasource": {
        "type": "prometheus",
        "uid": "ECOTRACK_PROM"
      },
      "gridPos": {
        "h": 4,
        "w": 4,
        "x": 4,
        "y": 0
      },
      "fieldConfig": {
        "defaults": {
          "unit": "short",
          "thresholds": {
            "mode": "absolute",
            "steps": [
              {
                "color": "blue",
                "value": null
              }
            ]
          },
          "color": {
            "mode": "thresholds"
          }
        },
        "overrides": []
      },
      "options": {
        "reduceOptions": {
          "calcs": [
            "lastNotNull"
          ],
          "fields": "",
          "values": false
        },
        "colorMode": "value",
        "graphMode": "none",
        "justifyMode": "auto",
        "textMode": "auto",
        "orientation": "auto"
      },
      "targets": [
        {
          "datasource": {
            "type": "prometheus",
            "uid": "ECOTRACK_PROM"
          },
          "editorMode": "code",
          "expr": "count(up)",
          "legendFormat": "__auto",
          "range": true,
          "instant": false,
          "refId": "A"
        }
      ],
      "id": 2
    },
    {
      "type": "gauge",
      "title": "Uptime moyen 24h",
      "datasource": {
        "type": "prometheus",
        "uid": "ECOTRACK_PROM"
      },
      "gridPos": {
        "h": 4,
        "w": 4,
        "x": 8,
        "y": 0
      },
      "fieldConfig": {
        "defaults": {
          "unit": "percent",
          "min": 0,
          "max": 100,
          "thresholds": {
            "mode": "absolute",
            "steps": [
              {
                "color": "red",
                "value": null
              },
              {
                "color": "orange",
                "value": 90
              },
              {
                "color": "green",
                "value": 99
              }
            ]
          },
          "color": {
            "mode": "thresholds"
          }
        },
        "overrides": []
      },
      "options": {
        "reduceOptions": {
          "calcs": [
            "lastNotNull"
          ],
          "fields": "",
          "values": false
        },
        "showThresholdMarkers": true
      },
      "targets": [
        {
          "datasource": {
            "type": "prometheus",
            "uid": "ECOTRACK_PROM"
          },
          "editorMode": "code",
          "expr": "avg(avg_over_time(up[24h]))*100",
          "legendFormat": "__auto",
          "range": true,
          "instant": false,
          "refId": "A"
        }
      ],
      "id": 3
    },
    {
      "type": "stat",
      "title": "API ingestion",
      "datasource": {
        "type": "prometheus",
        "uid": "ECOTRACK_PROM"
      },
      "gridPos": {
        "h": 4,
        "w": 4,
        "x": 12,
        "y": 0
      },
      "fieldConfig": {
        "defaults": {
          "unit": "short",
          "thresholds": {
            "mode": "absolute",
            "steps": [
              {
                "color": "red",
                "value": null
              },
              {
                "color": "green",
                "value": 1
              }
            ]
          },
          "color": {
            "mode": "thresholds"
          }
        },
        "overrides": []
      },
      "options": {
        "reduceOptions": {
          "calcs": [
            "lastNotNull"
          ],
          "fields": "",
          "values": false
        },
        "colorMode": "background",
        "graphMode": "none",
        "justifyMode": "auto",
        "textMode": "auto",
        "orientation": "auto"
      },
      "targets": [
        {
          "datasource": {
            "type": "prometheus",
            "uid": "ECOTRACK_PROM"
          },
          "editorMode": "code",
          "expr": "iot_api_up",
          "legendFormat": "__auto",
          "range": true,
          "instant": false,
          "refId": "A"
        }
      ],
      "id": 4
    },
    {
      "type": "stat",
      "title": "PostgreSQL",
      "datasource": {
        "type": "prometheus",
        "uid": "ECOTRACK_PROM"
      },
      "gridPos": {
        "h": 4,
        "w": 4,
        "x": 16,
        "y": 0
      },
      "fieldConfig": {
        "defaults": {
          "unit": "short",
          "thresholds": {
            "mode": "absolute",
            "steps": [
              {
                "color": "red",
                "value": null
              },
              {
                "color": "green",
                "value": 1
              }
            ]
          },
          "color": {
            "mode": "thresholds"
          }
        },
        "overrides": []
      },
      "options": {
        "reduceOptions": {
          "calcs": [
            "lastNotNull"
          ],
          "fields": "",
          "values": false
        },
        "colorMode": "background",
        "graphMode": "none",
        "justifyMode": "auto",
        "textMode": "auto",
        "orientation": "auto"
      },
      "targets": [
        {
          "datasource": {
            "type": "prometheus",
            "uid": "ECOTRACK_PROM"
          },
          "editorMode": "code",
          "expr": "pg_up",
          "legendFormat": "__auto",
          "range": true,
          "instant": false,
          "refId": "A"
        }
      ],
      "id": 5
    },
    {
      "type": "stat",
      "title": "Alertes actives",
      "datasource": {
        "type": "prometheus",
        "uid": "ECOTRACK_PROM"
      },
      "gridPos": {
        "h": 4,
        "w": 4,
        "x": 20,
        "y": 0
      },
      "fieldConfig": {
        "defaults": {
          "unit": "short",
          "thresholds": {
            "mode": "absolute",
            "steps": [
              {
                "color": "green",
                "value": null
              },
              {
                "color": "orange",
                "value": 1
              },
              {
                "color": "red",
                "value": 5
              }
            ]
          },
          "color": {
            "mode": "thresholds"
          }
        },
        "overrides": []
      },
      "options": {
        "reduceOptions": {
          "calcs": [
            "lastNotNull"
          ],
          "fields": "",
          "values": false
        },
        "colorMode": "background",
        "graphMode": "none",
        "justifyMode": "auto",
        "textMode": "auto",
        "orientation": "auto"
      },
      "targets": [
        {
          "datasource": {
            "type": "prometheus",
            "uid": "ECOTRACK_PROM"
          },
          "editorMode": "code",
          "expr": "count(ALERTS{alertstate=\"firing\"}) or on() vector(0)",
          "legendFormat": "__auto",
          "range": true,
          "instant": false,
          "refId": "A"
        }
      ],
      "id": 6
    },
    {
      "type": "table",
      "title": "Disponibilite par cible (up)",
      "datasource": {
        "type": "prometheus",
        "uid": "ECOTRACK_PROM"
      },
      "gridPos": {
        "h": 8,
        "w": 10,
        "x": 0,
        "y": 4
      },
      "fieldConfig": {
        "defaults": {
          "custom": {
            "align": "auto",
            "filterable": true
          }
        },
        "overrides": [
          {
            "matcher": {
              "id": "byName",
              "options": "Value"
            },
            "properties": [
              {
                "id": "displayName",
                "value": "etat"
              },
              {
                "id": "custom.cellOptions",
                "value": {
                  "type": "color-background"
                }
              },
              {
                "id": "thresholds",
                "value": {
                  "mode": "absolute",
                  "steps": [
                    {
                      "color": "red",
                      "value": null
                    },
                    {
                      "color": "green",
                      "value": 1
                    }
                  ]
                }
              },
              {
                "id": "mappings",
                "value": [
                  {
                    "type": "value",
                    "options": {
                      "0": {
                        "text": "DOWN"
                      },
                      "1": {
                        "text": "UP"
                      }
                    }
                  }
                ]
              }
            ]
          }
        ]
      },
      "options": {
        "showHeader": true
      },
      "transformations": [
        {
          "id": "organize",
          "options": {
            "excludeByName": {
              "Time": true,
              "__name__": true
            },
            "renameByName": {
              "job": "service",
              "instance": "cible"
            }
          }
        }
      ],
      "targets": [
        {
          "datasource": {
            "type": "prometheus",
            "uid": "ECOTRACK_PROM"
          },
          "editorMode": "code",
          "expr": "up",
          "legendFormat": "",
          "range": false,
          "instant": true,
          "refId": "A"
        }
      ],
      "id": 7
    },
    {
      "type": "timeseries",
      "title": "Disponibilite dans le temps",
      "datasource": {
        "type": "prometheus",
        "uid": "ECOTRACK_PROM"
      },
      "gridPos": {
        "h": 8,
        "w": 14,
        "x": 10,
        "y": 4
      },
      "fieldConfig": {
        "defaults": {
          "unit": "short",
          "color": {
            "mode": "palette-classic"
          },
          "custom": {
            "drawStyle": "line",
            "lineInterpolation": "smooth",
            "lineWidth": 2,
            "fillOpacity": 5,
            "showPoints": "never",
            "stacking": {
              "mode": "none",
              "group": "A"
            }
          },
          "thresholds": {
            "mode": "absolute",
            "steps": [
              {
                "color": "green",
                "value": null
              }
            ]
          },
          "min": 0,
          "max": 1
        },
        "overrides": []
      },
      "options": {
        "legend": {
          "displayMode": "list",
          "placement": "bottom",
          "calcs": [
            "mean",
            "max"
          ]
        },
        "tooltip": {
          "mode": "multi",
          "sort": "desc"
        }
      },
      "targets": [
        {
          "datasource": {
            "type": "prometheus",
            "uid": "ECOTRACK_PROM"
          },
          "editorMode": "code",
          "expr": "up",
          "legendFormat": "{{job}}",
          "range": true,
          "instant": false,
          "refId": "A"
        }
      ],
      "id": 8
    },
    {
      "type": "timeseries",
      "title": "Latence API ingestion (p50 / p95 / p99)",
      "datasource": {
        "type": "prometheus",
        "uid": "ECOTRACK_PROM"
      },
      "gridPos": {
        "h": 8,
        "w": 12,
        "x": 0,
        "y": 12
      },
      "fieldConfig": {
        "defaults": {
          "unit": "s",
          "color": {
            "mode": "palette-classic"
          },
          "custom": {
            "drawStyle": "line",
            "lineInterpolation": "smooth",
            "lineWidth": 2,
            "fillOpacity": 10,
            "showPoints": "never",
            "stacking": {
              "mode": "none",
              "group": "A"
            }
          },
          "thresholds": {
            "mode": "absolute",
            "steps": [
              {
                "color": "green",
                "value": null
              },
              {
                "color": "yellow",
                "value": 0.3
              },
              {
                "color": "orange",
                "value": 0.8
              },
              {
                "color": "red",
                "value": 1.5
              }
            ]
          }
        },
        "overrides": []
      },
      "options": {
        "legend": {
          "displayMode": "list",
          "placement": "bottom",
          "calcs": [
            "mean",
            "max"
          ]
        },
        "tooltip": {
          "mode": "multi",
          "sort": "desc"
        }
      },
      "targets": [
        {
          "datasource": {
            "type": "prometheus",
            "uid": "ECOTRACK_PROM"
          },
          "editorMode": "code",
          "expr": "histogram_quantile(0.50, sum(rate(iot_post_duration_seconds_bucket[5m])) by (le))",
          "legendFormat": "p50",
          "range": true,
          "instant": false,
          "refId": "A"
        },
        {
          "datasource": {
            "type": "prometheus",
            "uid": "ECOTRACK_PROM"
          },
          "editorMode": "code",
          "expr": "histogram_quantile(0.95, sum(rate(iot_post_duration_seconds_bucket[5m])) by (le))",
          "legendFormat": "p95",
          "range": true,
          "instant": false,
          "refId": "B"
        },
        {
          "datasource": {
            "type": "prometheus",
            "uid": "ECOTRACK_PROM"
          },
          "editorMode": "code",
          "expr": "histogram_quantile(0.99, sum(rate(iot_post_duration_seconds_bucket[5m])) by (le))",
          "legendFormat": "p99",
          "range": true,
          "instant": false,
          "refId": "C"
        }
      ],
      "id": 9
    },
    {
      "type": "timeseries",
      "title": "Debit d'ingestion (mesures/s)",
      "datasource": {
        "type": "prometheus",
        "uid": "ECOTRACK_PROM"
      },
      "gridPos": {
        "h": 8,
        "w": 7,
        "x": 12,
        "y": 12
      },
      "fieldConfig": {
        "defaults": {
          "unit": "reqps",
          "color": {
            "mode": "palette-classic"
          },
          "custom": {
            "drawStyle": "line",
            "lineInterpolation": "smooth",
            "lineWidth": 2,
            "fillOpacity": 20,
            "showPoints": "never",
            "stacking": {
              "mode": "none",
              "group": "A"
            }
          },
          "thresholds": {
            "mode": "absolute",
            "steps": [
              {
                "color": "green",
                "value": null
              }
            ]
          }
        },
        "overrides": []
      },
      "options": {
        "legend": {
          "displayMode": "list",
          "placement": "bottom",
          "calcs": [
            "mean",
            "max"
          ]
        },
        "tooltip": {
          "mode": "multi",
          "sort": "desc"
        }
      },
      "targets": [
        {
          "datasource": {
            "type": "prometheus",
            "uid": "ECOTRACK_PROM"
          },
          "editorMode": "code",
          "expr": "sum(rate(iot_readings_sent_total[1m]))",
          "legendFormat": "mesures/s",
          "range": true,
          "instant": false,
          "refId": "A"
        }
      ],
      "id": 10
    },
    {
      "type": "timeseries",
      "title": "Erreurs d'ingestion (/s)",
      "datasource": {
        "type": "prometheus",
        "uid": "ECOTRACK_PROM"
      },
      "gridPos": {
        "h": 8,
        "w": 5,
        "x": 19,
        "y": 12
      },
      "fieldConfig": {
        "defaults": {
          "unit": "reqps",
          "color": {
            "mode": "palette-classic"
          },
          "custom": {
            "drawStyle": "line",
            "lineInterpolation": "smooth",
            "lineWidth": 2,
            "fillOpacity": 15,
            "showPoints": "never",
            "stacking": {
              "mode": "none",
              "group": "A"
            }
          },
          "thresholds": {
            "mode": "absolute",
            "steps": [
              {
                "color": "green",
                "value": null
              },
              {
                "color": "orange",
                "value": 0.1
              },
              {
                "color": "red",
                "value": 1
              }
            ]
          }
        },
        "overrides": []
      },
      "options": {
        "legend": {
          "displayMode": "list",
          "placement": "bottom",
          "calcs": [
            "mean",
            "max"
          ]
        },
        "tooltip": {
          "mode": "multi",
          "sort": "desc"
        }
      },
      "targets": [
        {
          "datasource": {
            "type": "prometheus",
            "uid": "ECOTRACK_PROM"
          },
          "editorMode": "code",
          "expr": "sum(rate(iot_post_errors_total[5m]))",
          "legendFormat": "erreurs/s",
          "range": true,
          "instant": false,
          "refId": "A"
        }
      ],
      "id": 11
    },
    {
      "type": "gauge",
      "title": "CPU hote",
      "datasource": {
        "type": "prometheus",
        "uid": "ECOTRACK_PROM"
      },
      "gridPos": {
        "h": 7,
        "w": 5,
        "x": 0,
        "y": 20
      },
      "fieldConfig": {
        "defaults": {
          "unit": "percent",
          "min": 0,
          "max": 100,
          "thresholds": {
            "mode": "absolute",
            "steps": [
              {
                "color": "green",
                "value": null
              },
              {
                "color": "yellow",
                "value": 70
              },
              {
                "color": "orange",
                "value": 85
              },
              {
                "color": "red",
                "value": 95
              }
            ]
          },
          "color": {
            "mode": "thresholds"
          }
        },
        "overrides": []
      },
      "options": {
        "reduceOptions": {
          "calcs": [
            "lastNotNull"
          ],
          "fields": "",
          "values": false
        },
        "showThresholdMarkers": true
      },
      "targets": [
        {
          "datasource": {
            "type": "prometheus",
            "uid": "ECOTRACK_PROM"
          },
          "editorMode": "code",
          "expr": "100 - (avg(rate(node_cpu_seconds_total{mode=\"idle\"}[5m]))*100)",
          "legendFormat": "__auto",
          "range": true,
          "instant": false,
          "refId": "A"
        }
      ],
      "id": 12
    },
    {
      "type": "gauge",
      "title": "RAM hote",
      "datasource": {
        "type": "prometheus",
        "uid": "ECOTRACK_PROM"
      },
      "gridPos": {
        "h": 7,
        "w": 5,
        "x": 5,
        "y": 20
      },
      "fieldConfig": {
        "defaults": {
          "unit": "percent",
          "min": 0,
          "max": 100,
          "thresholds": {
            "mode": "absolute",
            "steps": [
              {
                "color": "green",
                "value": null
              },
              {
                "color": "yellow",
                "value": 70
              },
              {
                "color": "orange",
                "value": 85
              },
              {
                "color": "red",
                "value": 95
              }
            ]
          },
          "color": {
            "mode": "thresholds"
          }
        },
        "overrides": []
      },
      "options": {
        "reduceOptions": {
          "calcs": [
            "lastNotNull"
          ],
          "fields": "",
          "values": false
        },
        "showThresholdMarkers": true
      },
      "targets": [
        {
          "datasource": {
            "type": "prometheus",
            "uid": "ECOTRACK_PROM"
          },
          "editorMode": "code",
          "expr": "(1 - node_memory_MemAvailable_bytes / node_memory_MemTotal_bytes) * 100",
          "legendFormat": "__auto",
          "range": true,
          "instant": false,
          "refId": "A"
        }
      ],
      "id": 13
    },
    {
      "type": "gauge",
      "title": "Disque /",
      "datasource": {
        "type": "prometheus",
        "uid": "ECOTRACK_PROM"
      },
      "gridPos": {
        "h": 7,
        "w": 5,
        "x": 10,
        "y": 20
      },
      "fieldConfig": {
        "defaults": {
          "unit": "percent",
          "min": 0,
          "max": 100,
          "thresholds": {
            "mode": "absolute",
            "steps": [
              {
                "color": "green",
                "value": null
              },
              {
                "color": "yellow",
                "value": 70
              },
              {
                "color": "orange",
                "value": 85
              },
              {
                "color": "red",
                "value": 95
              }
            ]
          },
          "color": {
            "mode": "thresholds"
          }
        },
        "overrides": []
      },
      "options": {
        "reduceOptions": {
          "calcs": [
            "lastNotNull"
          ],
          "fields": "",
          "values": false
        },
        "showThresholdMarkers": true
      },
      "targets": [
        {
          "datasource": {
            "type": "prometheus",
            "uid": "ECOTRACK_PROM"
          },
          "editorMode": "code",
          "expr": "(1 - (node_filesystem_avail_bytes{mountpoint=\"/\",fstype!~\"tmpfs|overlay\"} / node_filesystem_size_bytes{mountpoint=\"/\",fstype!~\"tmpfs|overlay\"})) * 100",
          "legendFormat": "__auto",
          "range": true,
          "instant": false,
          "refId": "A"
        }
      ],
      "id": 14
    },
    {
      "type": "timeseries",
      "title": "Charge systeme (load1 / load5 / load15)",
      "datasource": {
        "type": "prometheus",
        "uid": "ECOTRACK_PROM"
      },
      "gridPos": {
        "h": 7,
        "w": 9,
        "x": 15,
        "y": 20
      },
      "fieldConfig": {
        "defaults": {
          "unit": "short",
          "color": {
            "mode": "palette-classic"
          },
          "custom": {
            "drawStyle": "line",
            "lineInterpolation": "smooth",
            "lineWidth": 2,
            "fillOpacity": 10,
            "showPoints": "never",
            "stacking": {
              "mode": "none",
              "group": "A"
            }
          },
          "thresholds": {
            "mode": "absolute",
            "steps": [
              {
                "color": "green",
                "value": null
              },
              {
                "color": "yellow",
                "value": 70
              },
              {
                "color": "orange",
                "value": 85
              },
              {
                "color": "red",
                "value": 95
              }
            ]
          }
        },
        "overrides": []
      },
      "options": {
        "legend": {
          "displayMode": "list",
          "placement": "bottom",
          "calcs": [
            "mean",
            "max"
          ]
        },
        "tooltip": {
          "mode": "multi",
          "sort": "desc"
        }
      },
      "targets": [
        {
          "datasource": {
            "type": "prometheus",
            "uid": "ECOTRACK_PROM"
          },
          "editorMode": "code",
          "expr": "node_load1",
          "legendFormat": "load1",
          "range": true,
          "instant": false,
          "refId": "A"
        },
        {
          "datasource": {
            "type": "prometheus",
            "uid": "ECOTRACK_PROM"
          },
          "editorMode": "code",
          "expr": "node_load5",
          "legendFormat": "load5",
          "range": true,
          "instant": false,
          "refId": "B"
        },
        {
          "datasource": {
            "type": "prometheus",
            "uid": "ECOTRACK_PROM"
          },
          "editorMode": "code",
          "expr": "node_load15",
          "legendFormat": "load15",
          "range": true,
          "instant": false,
          "refId": "C"
        }
      ],
      "id": 15
    },
    {
      "type": "timeseries",
      "title": "Trafic reseau hote",
      "datasource": {
        "type": "prometheus",
        "uid": "ECOTRACK_PROM"
      },
      "gridPos": {
        "h": 8,
        "w": 8,
        "x": 0,
        "y": 27
      },
      "fieldConfig": {
        "defaults": {
          "unit": "Bps",
          "color": {
            "mode": "palette-classic"
          },
          "custom": {
            "drawStyle": "line",
            "lineInterpolation": "smooth",
            "lineWidth": 2,
            "fillOpacity": 10,
            "showPoints": "never",
            "stacking": {
              "mode": "none",
              "group": "A"
            }
          },
          "thresholds": {
            "mode": "absolute",
            "steps": [
              {
                "color": "green",
                "value": null
              }
            ]
          }
        },
        "overrides": []
      },
      "options": {
        "legend": {
          "displayMode": "list",
          "placement": "bottom",
          "calcs": [
            "mean",
            "max"
          ]
        },
        "tooltip": {
          "mode": "multi",
          "sort": "desc"
        }
      },
      "targets": [
        {
          "datasource": {
            "type": "prometheus",
            "uid": "ECOTRACK_PROM"
          },
          "editorMode": "code",
          "expr": "rate(node_network_receive_bytes_total{device!~\"lo|veth.*\"}[5m])",
          "legendFormat": "rx {{device}}",
          "range": true,
          "instant": false,
          "refId": "A"
        },
        {
          "datasource": {
            "type": "prometheus",
            "uid": "ECOTRACK_PROM"
          },
          "editorMode": "code",
          "expr": "rate(node_network_transmit_bytes_total{device!~\"lo|veth.*\"}[5m])",
          "legendFormat": "tx {{device}}",
          "range": true,
          "instant": false,
          "refId": "B"
        }
      ],
      "id": 16
    },
    {
      "type": "timeseries",
      "title": "CPU par coeur",
      "datasource": {
        "type": "prometheus",
        "uid": "ECOTRACK_PROM"
      },
      "gridPos": {
        "h": 8,
        "w": 8,
        "x": 8,
        "y": 27
      },
      "fieldConfig": {
        "defaults": {
          "unit": "percent",
          "color": {
            "mode": "palette-classic"
          },
          "custom": {
            "drawStyle": "line",
            "lineInterpolation": "smooth",
            "lineWidth": 2,
            "fillOpacity": 8,
            "showPoints": "never",
            "stacking": {
              "mode": "none",
              "group": "A"
            }
          },
          "thresholds": {
            "mode": "absolute",
            "steps": [
              {
                "color": "green",
                "value": null
              }
            ]
          },
          "min": 0,
          "max": 100
        },
        "overrides": []
      },
      "options": {
        "legend": {
          "displayMode": "list",
          "placement": "bottom",
          "calcs": [
            "mean",
            "max"
          ]
        },
        "tooltip": {
          "mode": "multi",
          "sort": "desc"
        }
      },
      "targets": [
        {
          "datasource": {
            "type": "prometheus",
            "uid": "ECOTRACK_PROM"
          },
          "editorMode": "code",
          "expr": "100 - (avg by (cpu) (rate(node_cpu_seconds_total{mode=\"idle\"}[5m])) * 100)",
          "legendFormat": "coeur {{cpu}}",
          "range": true,
          "instant": false,
          "refId": "A"
        }
      ],
      "id": 17
    },
    {
      "type": "timeseries",
      "title": "Memoire hote (utilisee / cache / disponible)",
      "datasource": {
        "type": "prometheus",
        "uid": "ECOTRACK_PROM"
      },
      "gridPos": {
        "h": 8,
        "w": 8,
        "x": 16,
        "y": 27
      },
      "fieldConfig": {
        "defaults": {
          "unit": "bytes",
          "color": {
            "mode": "palette-classic"
          },
          "custom": {
            "drawStyle": "line",
            "lineInterpolation": "smooth",
            "lineWidth": 2,
            "fillOpacity": 15,
            "showPoints": "never",
            "stacking": {
              "mode": "normal",
              "group": "A"
            }
          },
          "thresholds": {
            "mode": "absolute",
            "steps": [
              {
                "color": "green",
                "value": null
              }
            ]
          }
        },
        "overrides": []
      },
      "options": {
        "legend": {
          "displayMode": "list",
          "placement": "bottom",
          "calcs": [
            "mean",
            "max"
          ]
        },
        "tooltip": {
          "mode": "multi",
          "sort": "desc"
        }
      },
      "targets": [
        {
          "datasource": {
            "type": "prometheus",
            "uid": "ECOTRACK_PROM"
          },
          "editorMode": "code",
          "expr": "node_memory_MemTotal_bytes - node_memory_MemAvailable_bytes",
          "legendFormat": "utilisee",
          "range": true,
          "instant": false,
          "refId": "A"
        },
        {
          "datasource": {
            "type": "prometheus",
            "uid": "ECOTRACK_PROM"
          },
          "editorMode": "code",
          "expr": "node_memory_Cached_bytes + node_memory_Buffers_bytes",
          "legendFormat": "cache + buffers",
          "range": true,
          "instant": false,
          "refId": "B"
        },
        {
          "datasource": {
            "type": "prometheus",
            "uid": "ECOTRACK_PROM"
          },
          "editorMode": "code",
          "expr": "node_memory_MemAvailable_bytes",
          "legendFormat": "disponible",
          "range": true,
          "instant": false,
          "refId": "C"
        }
      ],
      "id": 18
    },
    {
      "type": "timeseries",
      "title": "Requetes via le WAF (/s)",
      "datasource": {
        "type": "prometheus",
        "uid": "ECOTRACK_PROM"
      },
      "gridPos": {
        "h": 8,
        "w": 8,
        "x": 0,
        "y": 35
      },
      "fieldConfig": {
        "defaults": {
          "unit": "reqps",
          "color": {
            "mode": "palette-classic"
          },
          "custom": {
            "drawStyle": "line",
            "lineInterpolation": "smooth",
            "lineWidth": 2,
            "fillOpacity": 15,
            "showPoints": "never",
            "stacking": {
              "mode": "none",
              "group": "A"
            }
          },
          "thresholds": {
            "mode": "absolute",
            "steps": [
              {
                "color": "green",
                "value": null
              }
            ]
          }
        },
        "overrides": []
      },
      "options": {
        "legend": {
          "displayMode": "list",
          "placement": "bottom",
          "calcs": [
            "mean",
            "max"
          ]
        },
        "tooltip": {
          "mode": "multi",
          "sort": "desc"
        }
      },
      "targets": [
        {
          "datasource": {
            "type": "prometheus",
            "uid": "ECOTRACK_PROM"
          },
          "editorMode": "code",
          "expr": "rate(nginx_http_requests_total[1m])",
          "legendFormat": "req/s",
          "range": true,
          "instant": false,
          "refId": "A"
        }
      ],
      "id": 19
    },
    {
      "type": "timeseries",
      "title": "Connexions WAF (actives / lecture / ecriture / attente)",
      "datasource": {
        "type": "prometheus",
        "uid": "ECOTRACK_PROM"
      },
      "gridPos": {
        "h": 8,
        "w": 8,
        "x": 8,
        "y": 35
      },
      "fieldConfig": {
        "defaults": {
          "unit": "short",
          "color": {
            "mode": "palette-classic"
          },
          "custom": {
            "drawStyle": "line",
            "lineInterpolation": "smooth",
            "lineWidth": 2,
            "fillOpacity": 10,
            "showPoints": "never",
            "stacking": {
              "mode": "none",
              "group": "A"
            }
          },
          "thresholds": {
            "mode": "absolute",
            "steps": [
              {
                "color": "green",
                "value": null
              }
            ]
          }
        },
        "overrides": []
      },
      "options": {
        "legend": {
          "displayMode": "list",
          "placement": "bottom",
          "calcs": [
            "mean",
            "max"
          ]
        },
        "tooltip": {
          "mode": "multi",
          "sort": "desc"
        }
      },
      "targets": [
        {
          "datasource": {
            "type": "prometheus",
            "uid": "ECOTRACK_PROM"
          },
          "editorMode": "code",
          "expr": "nginx_connections_active",
          "legendFormat": "actives",
          "range": true,
          "instant": false,
          "refId": "A"
        },
        {
          "datasource": {
            "type": "prometheus",
            "uid": "ECOTRACK_PROM"
          },
          "editorMode": "code",
          "expr": "nginx_connections_reading",
          "legendFormat": "lecture",
          "range": true,
          "instant": false,
          "refId": "B"
        },
        {
          "datasource": {
            "type": "prometheus",
            "uid": "ECOTRACK_PROM"
          },
          "editorMode": "code",
          "expr": "nginx_connections_writing",
          "legendFormat": "ecriture",
          "range": true,
          "instant": false,
          "refId": "C"
        },
        {
          "datasource": {
            "type": "prometheus",
            "uid": "ECOTRACK_PROM"
          },
          "editorMode": "code",
          "expr": "nginx_connections_waiting",
          "legendFormat": "attente",
          "range": true,
          "instant": false,
          "refId": "D"
        }
      ],
      "id": 20
    },
    {
      "type": "timeseries",
      "title": "PostgreSQL : connexions & taille base",
      "datasource": {
        "type": "prometheus",
        "uid": "ECOTRACK_PROM"
      },
      "gridPos": {
        "h": 8,
        "w": 8,
        "x": 16,
        "y": 35
      },
      "fieldConfig": {
        "defaults": {
          "unit": "short",
          "color": {
            "mode": "palette-classic"
          },
          "custom": {
            "drawStyle": "line",
            "lineInterpolation": "smooth",
            "lineWidth": 2,
            "fillOpacity": 8,
            "showPoints": "never",
            "stacking": {
              "mode": "none",
              "group": "A"
            }
          },
          "thresholds": {
            "mode": "absolute",
            "steps": [
              {
                "color": "green",
                "value": null
              }
            ]
          }
        },
        "overrides": []
      },
      "options": {
        "legend": {
          "displayMode": "list",
          "placement": "bottom",
          "calcs": [
            "mean",
            "max"
          ]
        },
        "tooltip": {
          "mode": "multi",
          "sort": "desc"
        }
      },
      "targets": [
        {
          "datasource": {
            "type": "prometheus",
            "uid": "ECOTRACK_PROM"
          },
          "editorMode": "code",
          "expr": "sum(pg_stat_database_numbackends)",
          "legendFormat": "connexions actives",
          "range": true,
          "instant": false,
          "refId": "A"
        },
        {
          "datasource": {
            "type": "prometheus",
            "uid": "ECOTRACK_PROM"
          },
          "editorMode": "code",
          "expr": "sum(pg_database_size_bytes{datname=\"ecotrack\"})",
          "legendFormat": "taille base (octets)",
          "range": true,
          "instant": false,
          "refId": "B"
        }
      ],
      "id": 21
    },
    {
      "type": "timeseries",
      "title": "Conteneurs - CPU global",
      "datasource": {
        "type": "prometheus",
        "uid": "ECOTRACK_PROM"
      },
      "gridPos": {
        "h": 7,
        "w": 12,
        "x": 0,
        "y": 43
      },
      "fieldConfig": {
        "defaults": {
          "unit": "percent",
          "color": {
            "mode": "palette-classic"
          },
          "custom": {
            "drawStyle": "line",
            "lineInterpolation": "smooth",
            "lineWidth": 2,
            "fillOpacity": 15,
            "showPoints": "never",
            "stacking": {
              "mode": "none",
              "group": "A"
            }
          },
          "thresholds": {
            "mode": "absolute",
            "steps": [
              {
                "color": "green",
                "value": null
              }
            ]
          }
        },
        "overrides": []
      },
      "options": {
        "legend": {
          "displayMode": "list",
          "placement": "bottom",
          "calcs": [
            "mean",
            "max"
          ]
        },
        "tooltip": {
          "mode": "multi",
          "sort": "desc"
        }
      },
      "targets": [
        {
          "datasource": {
            "type": "prometheus",
            "uid": "ECOTRACK_PROM"
          },
          "editorMode": "code",
          "expr": "sum(rate(container_cpu_usage_seconds_total{id=\"/docker\"}[5m])) * 100",
          "legendFormat": "CPU conteneurs %",
          "range": true,
          "instant": false,
          "refId": "A"
        }
      ],
      "id": 22
    },
    {
      "type": "timeseries",
      "title": "Conteneurs - memoire globale",
      "datasource": {
        "type": "prometheus",
        "uid": "ECOTRACK_PROM"
      },
      "gridPos": {
        "h": 7,
        "w": 12,
        "x": 12,
        "y": 43
      },
      "fieldConfig": {
        "defaults": {
          "unit": "bytes",
          "color": {
            "mode": "palette-classic"
          },
          "custom": {
            "drawStyle": "line",
            "lineInterpolation": "smooth",
            "lineWidth": 2,
            "fillOpacity": 12,
            "showPoints": "never",
            "stacking": {
              "mode": "none",
              "group": "A"
            }
          },
          "thresholds": {
            "mode": "absolute",
            "steps": [
              {
                "color": "green",
                "value": null
              }
            ]
          }
        },
        "overrides": []
      },
      "options": {
        "legend": {
          "displayMode": "list",
          "placement": "bottom",
          "calcs": [
            "mean",
            "max"
          ]
        },
        "tooltip": {
          "mode": "multi",
          "sort": "desc"
        }
      },
      "targets": [
        {
          "datasource": {
            "type": "prometheus",
            "uid": "ECOTRACK_PROM"
          },
          "editorMode": "code",
          "expr": "container_memory_working_set_bytes{id=\"/docker\"}",
          "legendFormat": "memoire conteneurs",
          "range": true,
          "instant": false,
          "refId": "A"
        },
        {
          "datasource": {
            "type": "prometheus",
            "uid": "ECOTRACK_PROM"
          },
          "editorMode": "code",
          "expr": "container_memory_working_set_bytes{id=\"/\"}",
          "legendFormat": "memoire machine",
          "range": true,
          "instant": false,
          "refId": "B"
        }
      ],
      "id": 23
    }
  ]
}